protected_method_metaclass/__init__.py
protected_method_metaclass/protected_decorator.py
protected_method_metaclass/protected_method_metaclass.py
protected_method_metaclass/protected_method_metaclass_pyside2.py
protected_method_metaclass/protected_method_metaclass_qt.py
protected_method_metaclass-1.0.dist-info/METADATA
protected_method_metaclass-1.0.dist-info/WHEEL
protected_method_metaclass-1.0.dist-info/top_level.txt
protected_method_metaclass-1.0.dist-info/RECORD
